[
    {"u1":"Transparencia/48RDTL/transparencia.html","u2":"img/menu/transparencia.jpg"},
    {"u1":"PDF/calendario.pdf","u2":"img/menu/calendar.jpg"},
    {"u1":"/ArmonizacionContable/","u2":"img/menu/conac.jpg"},
    {"u1":"Formato/Formatos_Estadia_UPE.zip","u2":"img/menu/docEstadia.jpg"},
    {"u1":"/Indicadores/","u2":"img/menu/indicadores.jpg"},
    {"u1":"PDF/PAAyS_UPE_2022.pdf","u2":"img/menu/paaays.jpg"},
    {"u1":"PDF/GUIA_TITULOELECTRONICO.pdf","u2":"img/menu/guiaTitulo.jpg"},
    {"u1":"PDF/T_Constancia-Historial.pdf","u2":"img/menu/tse.jpg"},
    {"u1":"/CeroTolerancia/","u2":"img/menu/cero.jpg"},
    {"u1":"/ContraloriaSocial/","u2":"img/menu/cs.jpg"},
    {"u1":"PDF/rer.pdf","u2":"img/menu/revalidacion.jpg"},
    {"u1":"/Vacantes/","u2":"img/menu/vacantes.jpg"},
    {"u1":"/Archivo/","u2":"img/menu/archivo.jpg"},
    {"u1":"/Calidad/","u2":"img/menu/calidad.jpg"},
    {"u1":"SIAUPE/login.aspx","u2":"img/menu/siaa.jpg"}
]